[
    {
        "annotations": [
            {
                "class": "title",
                "height": 251.4964036014285,
                "id": "0",
                "type": "rect",
                "width": 5095.317136964943,
                "x": 125.74820180071427,
                "y": 226.3467632412857
            },
            {
                "class": "title",
                "height": 347.0650369699713,
                "id": "1",
                "type": "rect",
                "width": 628.7410090035713,
                "x": 145.86791408882854,
                "y": 563.3519440672
            },
            {
                "class": "article",
                "height": 980.8359740455713,
                "id": "1",
                "type": "rect",
                "width": 648.8607212916856,
                "x": 155.92777023288568,
                "y": 925.506765253257
            },
            {
                "class": "article",
                "height": 549.3680305619862,
                "id": "1",
                "type": "rect",
                "width": 331.76121326145903,
                "x": 160.52961932006085,
                "y": 1915.6534572193925
            },
            {
                "class": "graphics",
                "height": 542.2333808144278,
                "id": "1",
                "type": "rect",
                "width": 306.7899391450051,
                "x": 495.858157455299,
                "y": 1915.6534572193925
            },
            {
                "class": "article",
                "height": 1005.9856144057144,
                "id": "1",
                "type": "rect",
                "width": 638.5511524064642,
                "x": 167.6642690676191,
                "y": 2465.0214877813787
            },
            {
                "class": "article",
                "height": 795.5134468527453,
                "id": "1",
                "type": "rect",
                "width": 634.9838275326852,
                "x": 171.23159394139822,
                "y": 3510.2476757986637
            },
            {
                "class": "article",
                "height": 1030.9568885221688,
                "id": "1",
                "type": "rect",
                "width": 649.2531270278016,
                "x": 167.6642690676191,
                "y": 4334.2997216416425
            },
            {
                "class": "title",
                "height": 74.91382234936191,
                "id": "2",
                "type": "rect",
                "width": 381.70376149436686,
                "x": 313.9245888925634,
                "y": 5408.06450864916
            },
            {
                "class": "title",
                "height": 203.33751780541024,
                "id": "3",
                "type": "rect",
                "width": 577.906629552219,
                "x": 228.3087919218643,
                "y": 6107.26018390987
            },
            {
                "class": "article",
                "height": 531.5314061930903,
                "id": "2",
                "type": "rect",
                "width": 570.7719798046608,
                "x": 221.17414217430604,
                "y": 5500.8149553674175
            },
            {
                "class": "article",
                "height": 727.7342742509427,
                "id": "3",
                "type": "rect",
                "width": 585.0412792997772,
                "x": 228.3087919218643,
                "y": 6324.867001210397
            },
            {
                "class": "title",
                "height": 542.2333808144278,
                "id": "4",
                "type": "rect",
                "width": 863.2926194545495,
                "x": 813.3500712216415,
                "y": 545.8007056882068
            },
            {
                "class": "graphics",
                "height": 535.0987310668694,
                "id": "4",
                "type": "rect",
                "width": 335.3285381352382,
                "x": 1687.3446652975283,
                "y": 560.0700051833234
            },
            {
                "class": "article",
                "height": 2051.2118024229994,
                "id": "4",
                "type": "rect",
                "width": 1259.2656804440326,
                "x": 809.7827463478625,
                "y": 1113.0053606190884
            },
            {
                "class": "article",
                "height": 2079.750401413233,
                "id": "4",
                "type": "rect",
                "width": 1280.6696296867076,
                "x": 813.3500712216415,
                "y": 3174.9191376634253
            },
            {
                "class": "title",
                "height": 78.4811472231413,
                "id": "5",
                "type": "rect",
                "width": 556.5026803095442,
                "x": 873.9945940758868,
                "y": 5308.1794121833445
            },
            {
                "class": "article",
                "height": 1690.9119901713075,
                "id": "5",
                "type": "rect",
                "width": 649.2531270278016,
                "x": 827.6193707167581,
                "y": 5400.9298589016025
            },
            {
                "class": "title",
                "height": 107.01974621337376,
                "id": "6",
                "type": "rect",
                "width": 456.61758384372865,
                "x": 1544.651670346363,
                "y": 5301.044762435787
            },
            {
                "class": "article",
                "height": 1669.508040928633,
                "id": "6",
                "type": "rect",
                "width": 652.8204519015806,
                "x": 1459.035873375664,
                "y": 5422.333808144277
            },
            {
                "class": "title",
                "height": 542.2333808144277,
                "id": "7",
                "type": "rect",
                "width": 599.3105787948939,
                "x": 2069.048426791895,
                "y": 520.8294315717529
            },
            {
                "class": "article",
                "height": 1962.0286805785213,
                "id": "7",
                "type": "rect",
                "width": 649.2531270278014,
                "x": 2061.913777044337,
                "y": 1073.764787007518
            },
            {
                "class": "article",
                "height": 1177.2172083471128,
                "id": "7",
                "type": "rect",
                "width": 642.118477280243,
                "x": 2079.750401413233,
                "y": 3039.3607924598186
            },
            {
                "class": "article",
                "height": 1366.2854266574068,
                "id": "7",
                "type": "rect",
                "width": 642.1184772802435,
                "x": 2086.8850511607907,
                "y": 4241.549274923385
            },
            {
                "class": "title",
                "height": 160.5296193200611,
                "id": "8",
                "type": "rect",
                "width": 631.4165026589058,
                "x": 2101.1543506559074,
                "y": 5650.642600066141
            },
            {
                "class": "article",
                "height": 1262.8330053178115,
                "id": "8",
                "type": "rect",
                "width": 642.1184772802435,
                "x": 2104.7216755296863,
                "y": 5825.441518881319
            },
            {
                "class": "title",
                "height": 545.8007056882068,
                "id": "9",
                "type": "rect",
                "width": 841.8886702118748,
                "x": 2704.03225432458,
                "y": 531.5314061930903
            },
            {
                "class": "graphics",
                "height": 510.12745695041554,
                "id": "9",
                "type": "rect",
                "width": 331.76121326145903,
                "x": 3560.1902240315712,
                "y": 552.9353554357651
            },
            {
                "class": "article",
                "height": 749.1382234936173,
                "id": "9",
                "type": "rect",
                "width": 1262.833005317812,
                "x": 2693.330279703243,
                "y": 1098.736061123972
            },
            {
                "class": "article",
                "height": 581.4739544259983,
                "id": "9",
                "type": "rect",
                "width": 1262.833005317812,
                "x": 2700.4649294508013,
                "y": 1858.5762592389265
            },
            {
                "class": "title",
                "height": 110.58707108715316,
                "id": "9",
                "type": "rect",
                "width": 1230.7270814538,
                "x": 2714.7342289459175,
                "y": 2450.752188286262
            },
            {
                "class": "article",
                "height": 1580.3249190841548,
                "id": "9",
                "type": "rect",
                "width": 1273.5349799391493,
                "x": 2714.7342289459175,
                "y": 2564.906584247194
            },
            {
                "class": "title",
                "height": 99.88509646581588,
                "id": "9",
                "type": "rect",
                "width": 1145.1112844831005,
                "x": 2729.003528441034,
                "y": 4155.933477952686
            },
            {
                "class": "article",
                "height": 346.0305127565762,
                "id": "9",
                "type": "rect",
                "width": 1262.833005317812,
                "x": 2729.003528441034,
                "y": 4248.683924670943
            },
            {
                "class": "title",
                "height": 149.8276446987229,
                "id": "10",
                "type": "rect",
                "width": 692.061025513151,
                "x": 3021.524168090923,
                "y": 4616.118386670194
            },
            {
                "class": "title",
                "height": 96.31777159203648,
                "id": "10",
                "type": "rect",
                "width": 585.0412792997772,
                "x": 2764.6767771788254,
                "y": 5522.218904610093
            },
            {
                "class": "title",
                "height": 71.34649747558251,
                "id": "10",
                "type": "rect",
                "width": 620.7145280375685,
                "x": 2761.1094523050465,
                "y": 6738.676686568776
            },
            {
                "class": "title",
                "height": 299.6552893974467,
                "id": "10",
                "type": "rect",
                "width": 585.0412792997772,
                "x": 3406.795254459069,
                "y": 6018.077062065392
            },
            {
                "class": "title",
                "height": 174.79891881517688,
                "id": "10",
                "type": "rect",
                "width": 563.6373300571022,
                "x": 3413.9299042066273,
                "y": 6449.7233717926665
            },
            {
                "class": "article",
                "height": 713.464974755826,
                "id": "10",
                "type": "rect",
                "width": 631.4165026589058,
                "x": 2729.003528441034,
                "y": 4769.513356242696
            },
            {
                "class": "article",
                "height": 1198.6211575897878,
                "id": "10",
                "type": "rect",
                "width": 634.9838275326852,
                "x": 3367.5546808474983,
                "y": 4783.782655737813
            },
            {
                "class": "article",
                "height": 1091.601411376414,
                "id": "10",
                "type": "rect",
                "width": 638.5511524064641,
                "x": 2736.1381781885925,
                "y": 5625.671325949687
            },
            {
                "class": "article",
                "height": 263.98204065965547,
                "id": "10",
                "type": "rect",
                "width": 624.2818529113474,
                "x": 2753.974802557488,
                "y": 6827.8598084132545
            },
            {
                "class": "article",
                "height": 388.8384112419253,
                "id": "10",
                "type": "rect",
                "width": 567.2046549308816,
                "x": 3413.9299042066273,
                "y": 6638.79159010296
            },
            {
                "class": "title",
                "height": 485.1561828339618,
                "id": "11",
                "type": "rect",
                "width": 567.2046549308816,
                "x": 3959.730609894834,
                "y": 545.8007056882068
            },
            {
                "class": "article",
                "height": 1523.2477211036883,
                "id": "11",
                "type": "rect",
                "width": 645.6858021540224,
                "x": 3956.163285021055,
                "y": 1034.5242133959475
            },
            {
                "class": "article",
                "height": 902.53319306612,
                "id": "11",
                "type": "rect",
                "width": 638.5511524064636,
                "x": 3981.134559137509,
                "y": 2575.6085588685314
            },
            {
                "class": "title",
                "height": 164.09694419384005,
                "id": "12",
                "type": "rect",
                "width": 420.94433510593717,
                "x": 4102.423604845999,
                "y": 3488.8437265559887
            },
            {
                "class": "article",
                "height": 1705.1812896664242,
                "id": "12",
                "type": "rect",
                "width": 649.2531270278018,
                "x": 3991.836533758846,
                "y": 3649.37334587605
            },
            {
                "class": "title",
                "height": 192.63554318407296,
                "id": "13",
                "type": "rect",
                "width": 570.7719798046605,
                "x": 4041.779081991754,
                "y": 5390.227884280265
            },
            {
                "class": "article",
                "height": 417.3770102321587,
                "id": "13",
                "type": "rect",
                "width": 585.0412792997772,
                "x": 4038.2117571179747,
                "y": 5600.700051833233
            },
            {
                "class": "title",
                "height": 927.5044671825735,
                "id": "14",
                "type": "rect",
                "width": 1123.707335240426,
                "x": 4109.558254593558,
                "y": 6089.423559540975
            },
            {
                "class": "title",
                "height": 117.72172083471128,
                "id": "15",
                "type": "rect",
                "width": 545.8007056882061,
                "x": 4594.714437427519,
                "y": 535.0987310668695
            },
            {
                "class": "article",
                "height": 1259.265680444033,
                "id": "15",
                "type": "rect",
                "width": 681.3590508918132,
                "x": 4580.445137932403,
                "y": 674.2244011442555
            },
            {
                "class": "title",
                "height": 92.75044671825754,
                "id": "16",
                "type": "rect",
                "width": 478.021533086403,
                "x": 4673.19558465066,
                "y": 1954.894030830963
            },
            {
                "class": "title",
                "height": 92.75044671825754,
                "id": "16",
                "type": "rect",
                "width": 520.829431571753,
                "x": 4676.762909524439,
                "y": 2322.3284928302132
            },
            {
                "class": "title",
                "height": 82.0484720969198,
                "id": "16",
                "type": "rect",
                "width": 463.7522335912872,
                "x": 4694.599533893334,
                "y": 2668.359005586789
            },
            {
                "class": "title",
                "height": 139.12567007738608,
                "id": "16",
                "type": "rect",
                "width": 538.6660559406482,
                "x": 4662.493610029323,
                "y": 3032.2261427122603
            },
            {
                "class": "title",
                "height": 288.95331477610944,
                "id": "16",
                "type": "rect",
                "width": 563.6373300571031,
                "x": 4658.926285155543,
                "y": 3388.9586300901733
            },
            {
                "class": "title",
                "height": 873.9945940758867,
                "id": "16",
                "type": "rect",
                "width": 560.0700051833237,
                "x": 4683.897559271997,
                "y": 3759.9604169632025
            },
            {
                "class": "article",
                "height": 199.7701929316313,
                "id": "16",
                "type": "rect",
                "width": 574.3393046784404,
                "x": 4633.955011039089,
                "y": 2058.3464521705578
            },
            {
                "class": "article",
                "height": 203.3375178054107,
                "id": "16",
                "type": "rect",
                "width": 574.3393046784395,
                "x": 4641.089660786648,
                "y": 2418.6462644222497
            },
            {
                "class": "article",
                "height": 214.03949242674798,
                "id": "16",
                "type": "rect",
                "width": 585.0412792997777,
                "x": 4633.955011039089,
                "y": 2750.4074776837087
            },
            {
                "class": "article",
                "height": 153.39496957250276,
                "id": "16",
                "type": "rect",
                "width": 577.9066295522189,
                "x": 4648.224310534206,
                "y": 3174.9191376634253
            },
            {
                "class": "graphics",
                "height": 378.13643662058803,
                "id": "17",
                "type": "rect",
                "width": 438.78095947483325,
                "x": 4740.974757252463,
                "y": 4705.301508514672
            },
            {
                "class": "article",
                "height": 859.7252945807704,
                "id": "17",
                "type": "rect",
                "width": 460.1849087175078,
                "x": 4733.840107504905,
                "y": 5104.841894377934
            },
            {
                "class": "graphics",
                "height": 358.3625196027742,
                "id": "18",
                "type": "rect",
                "width": 5106.665904339534,
                "x": 215.0175117616646,
                "y": 7101.550596794978
            }
        ],
        "class": "image",
        "filename": "0036.jpg"
    }
]
