[
    {
        "annotations": [
            {
                "class": "title",
                "height": 183.07522804762695,
                "id": "0",
                "type": "rect",
                "width": 1071.8222442061067,
                "x": 262.9626002865914,
                "y": 189.73250906754063
            },
            {
                "class": "title",
                "height": 143.1315419281447,
                "id": "0",
                "type": "rect",
                "width": 772.24459830999,
                "x": 189.73250906754063,
                "y": 396.10822068486556
            },
            {
                "class": "article",
                "height": 1830.7522804762693,
                "id": "0",
                "type": "rect",
                "width": 655.7421804615001,
                "x": 139.80290141818782,
                "y": 542.568403122967
            },
            {
                "class": "article",
                "height": 1887.3391691455363,
                "id": "0",
                "type": "rect",
                "width": 649.0848994415866,
                "x": 123.15969886840362,
                "y": 2399.9498076788923
            },
            {
                "class": "article",
                "height": 1251.5688317437773,
                "id": "0",
                "type": "rect",
                "width": 629.1130563818455,
                "x": 805.5310034095588,
                "y": 1171.681459504813
            },
            {
                "class": "article",
                "height": 1837.4095614961839,
                "id": "0",
                "type": "rect",
                "width": 642.4276184216728,
                "x": 778.901879329904,
                "y": 2439.8934937983745
            },
            {
                "class": "title",
                "height": 59.91552917922343,
                "id": "1",
                "type": "rect",
                "width": 432.7232662943911,
                "x": 818.8455654493862,
                "y": 582.5120892424495
            },
            {
                "class": "article",
                "height": 472.66695241387333,
                "id": "1",
                "type": "rect",
                "width": 642.427618421673,
                "x": 808.8596439195156,
                "y": 655.7421804615003
            },
            {
                "class": "title",
                "height": 116.50241784849004,
                "id": "2",
                "type": "rect",
                "width": 1018.5639960467976,
                "x": 119.83105835844677,
                "y": 4330.561303453867
            },
            {
                "class": "article",
                "height": 1155.0382569550284,
                "id": "2",
                "type": "rect",
                "width": 659.0708209714571,
                "x": 106.51649631861935,
                "y": 4457.0496428322285
            },
            {
                "class": "article",
                "height": 1687.6207385481257,
                "id": "2",
                "type": "rect",
                "width": 642.427618421673,
                "x": 772.2445983099902,
                "y": 4463.706923852142
            },
            {
                "class": "title",
                "height": 86.54465325887759,
                "id": "2",
                "type": "rect",
                "width": 569.1975272026222,
                "x": 99.85921529870564,
                "y": 5615.416540297214
            },
            {
                "class": "article",
                "height": 426.0659852744775,
                "id": "2",
                "type": "rect",
                "width": 256.3053192666778,
                "x": 99.85921529870564,
                "y": 5718.604396105876
            },
            {
                "class": "graphics",
                "height": 429.39462578443363,
                "id": "2",
                "type": "rect",
                "width": 356.1645345653834,
                "x": 369.4790966052109,
                "y": 5715.27575559592
            },
            {
                "class": "title",
                "height": 186.40386855758388,
                "id": "3",
                "type": "rect",
                "width": 2240.1750632009635,
                "x": 1464.601824381016,
                "y": 179.74658753767014
            },
            {
                "class": "article",
                "height": 1078.479525226021,
                "id": "3",
                "type": "rect",
                "width": 1444.629981321275,
                "x": 1467.9304648909729,
                "y": 382.79365864503825
            },
            {
                "class": "article",
                "height": 1867.3673260857954,
                "id": "3",
                "type": "rect",
                "width": 961.977107377531,
                "x": 2922.5463677421185,
                "y": 382.79365864503825
            },
            {
                "class": "graphics",
                "height": 1834.080920986227,
                "id": "3",
                "type": "rect",
                "width": 1418.00085724162,
                "x": 1451.2872623411886,
                "y": 1494.5595889706276
            },
            {
                "class": "title",
                "height": 266.29124079654866,
                "id": "4",
                "type": "rect",
                "width": 945.3339048277467,
                "x": 2909.231805702291,
                "y": 2273.4614683005316
            },
            {
                "class": "article",
                "height": 792.2164413697315,
                "id": "4",
                "type": "rect",
                "width": 968.6343883974446,
                "x": 2912.560446212248,
                "y": 2549.7386306269505
            },
            {
                "class": "article",
                "height": 1424.6581382615336,
                "id": "4",
                "type": "rect",
                "width": 499.29607649352783,
                "x": 3395.213320155992,
                "y": 3351.9409935265526
            },
            {
                "class": "title",
                "height": 193.06114957749787,
                "id": "5",
                "type": "rect",
                "width": 1940.5974173048464,
                "x": 1437.972700301361,
                "y": 3348.6123530165955
            },
            {
                "class": "title",
                "height": 133.14562039827342,
                "id": "5",
                "type": "rect",
                "width": 439.38054731430475,
                "x": 1427.9867787714907,
                "y": 4833.186020457353
            },
            {
                "class": "title",
                "height": 116.50241784849004,
                "id": "5",
                "type": "rect",
                "width": 372.8077371151676,
                "x": 1424.6581382615338,
                "y": 5645.3743048868255
            },
            {
                "class": "article",
                "height": 1264.8833937836048,
                "id": "5",
                "type": "rect",
                "width": 482.652873943744,
                "x": 1434.6440597914043,
                "y": 3561.6453456538343
            },
            {
                "class": "article",
                "height": 342.84997252555604,
                "id": "5",
                "type": "rect",
                "width": 1454.6159028511454,
                "x": 1927.2828552650187,
                "y": 3561.6453456538343
            },
            {
                "class": "article",
                "height": 662.3994614814137,
                "id": "5",
                "type": "rect",
                "width": 479.32423343378696,
                "x": 1427.9867787714907,
                "y": 4976.317562385498
            },
            {
                "class": "article",
                "height": 399.436861194823,
                "id": "5",
                "type": "rect",
                "width": 466.0096713939595,
                "x": 1424.6581382615338,
                "y": 5771.862644265186
            },
            {
                "class": "title",
                "height": 193.06114957749742,
                "id": "6",
                "type": "rect",
                "width": 1431.3154192814477,
                "x": 1930.6114957749755,
                "y": 3931.1244422590453
            },
            {
                "class": "title",
                "height": 49.929607649352874,
                "id": "6",
                "type": "rect",
                "width": 329.53541048572856,
                "x": 1927.2828552650187,
                "y": 4823.200098927482
            },
            {
                "class": "title",
                "height": 46.600967139395834,
                "id": "6",
                "type": "rect",
                "width": 302.90628640607383,
                "x": 1923.954214755062,
                "y": 5745.233520185531
            },
            {
                "class": "title",
                "height": 46.600967139395834,
                "id": "6",
                "type": "rect",
                "width": 436.05190680434816,
                "x": 2409.9357292087625,
                "y": 4969.660281365584
            },
            {
                "class": "title",
                "height": 49.929607649352874,
                "id": "6",
                "type": "rect",
                "width": 302.90628640607383,
                "x": 2895.9172436624635,
                "y": 5642.045664376868
            },
            {
                "class": "article",
                "height": 665.7281019913707,
                "id": "6",
                "type": "rect",
                "width": 456.02374986408904,
                "x": 1930.6114957749755,
                "y": 4140.828794386327
            },
            {
                "class": "article",
                "height": 852.131970548955,
                "id": "6",
                "type": "rect",
                "width": 466.0096713939595,
                "x": 1920.625574245105,
                "y": 4876.458347086792
            },
            {
                "class": "article",
                "height": 369.47909660521145,
                "id": "6",
                "type": "rect",
                "width": 466.00967139395993,
                "x": 1910.6396527152344,
                "y": 5801.820408854797
            },
            {
                "class": "article",
                "height": 832.1601274892137,
                "id": "6",
                "type": "rect",
                "width": 472.66695241387333,
                "x": 2409.9357292087625,
                "y": 4137.50015387637
            },
            {
                "class": "article",
                "height": 1148.3809759351152,
                "id": "6",
                "type": "rect",
                "width": 469.33831190391675,
                "x": 2403.278448188849,
                "y": 5022.9185295248935
            },
            {
                "class": "article",
                "height": 1497.8882294805844,
                "id": "6",
                "type": "rect",
                "width": 479.32423343378696,
                "x": 2895.9172436624635,
                "y": 4134.171513366414
            },
            {
                "class": "article",
                "height": 469.3383119039163,
                "id": "6",
                "type": "rect",
                "width": 475.9955929238304,
                "x": 2885.931322132593,
                "y": 5698.632553046135
            },
            {
                "class": "article",
                "height": 1098.4513682857614,
                "id": "4",
                "type": "rect",
                "width": 499.2960764935283,
                "x": 3385.227398626121,
                "y": 5079.5054181941605
            },
            {
                "class": "graphics",
                "height": 272.94852181646274,
                "id": "4",
                "type": "rect",
                "width": 472.66695241387333,
                "x": 3401.8706011759054,
                "y": 4803.228255867741
            }
        ],
        "class": "image",
        "filename": "0050.jpg"
    }
]
