[
    {
        "annotations": [
            {
                "x": 748.1533101045296,
                "height": 312.0,
                "type": "rect",
                "id": 0,
                "y": 204.0,
                "class": "article",
                "width": 3348.6862061897928
            },
            {
                "x": 97.01988112318098,
                "height": 366.0,
                "type": "rect",
                "id": 1,
                "y": 264.0,
                "class": "article",
                "width": 4575.937692150031
            },
            {
                "x": 88.01803648288583,
                "height": 120.0,
                "type": "rect",
                "id": 2,
                "y": 662.0,
                "class": "article",
                "width": 544.1114982578397
            },
            {
                "x": 64.01311744209879,
                "height": 6254.0,
                "type": "rect",
                "id": 3,
                "y": 862.0,
                "class": "article",
                "width": 577.1182619389219
            },
            {
                "x": 663.1358885017421,
                "height": 225.0,
                "type": "rect",
                "id": 4,
                "y": 666.0,
                "class": "article",
                "width": 1065.2182824349252
            },
            {
                "x": 807.1654027464645,
                "height": 118.0,
                "type": "rect",
                "id": 5,
                "y": 921.0,
                "class": "article",
                "width": 993.203525312564
            },
            {
                "x": 654.134043861447,
                "height": 1471.0,
                "type": "rect",
                "id": 6,
                "y": 1053.0,
                "class": "article",
                "width": 574.1176470588235
            },
            {
                "x": 786.1610985857758,
                "height": 115.0,
                "type": "rect",
                "id": 7,
                "y": 2535.0,
                "class": "article",
                "width": 1010.2070096331215
            },
            {
                "x": 650.1332240213159,
                "height": 1695.0,
                "type": "rect",
                "id": 8,
                "y": 2669.0,
                "class": "article",
                "width": 570.1168272186924
            },
            {
                "x": 655.1342488214798,
                "height": 106.0,
                "type": "rect",
                "id": 9,
                "y": 4399.0,
                "class": "article",
                "width": 1066.218487394958
            },
            {
                "x": 649.133019061283,
                "height": 2584.0,
                "type": "rect",
                "id": 10,
                "y": 4528.0,
                "class": "article",
                "width": 573.1174420987908
            },
            {
                "x": 1240.254150440664,
                "height": 99.0,
                "type": "rect",
                "id": 11,
                "y": 1055.0,
                "class": "article",
                "width": 552.113137938102
            },
            {
                "x": 1228.2516909202704,
                "height": 3202.0,
                "type": "rect",
                "id": 12,
                "y": 1159.0,
                "class": "article",
                "width": 573.1174420987908
            },
            {
                "x": 1199.2457470793195,
                "height": 127.0,
                "type": "rect",
                "id": 13,
                "y": 4528.0,
                "class": "article",
                "width": 596.122156179545
            },
            {
                "x": 1226.251281000205,
                "height": 2442.0,
                "type": "rect",
                "id": 14,
                "y": 4669.0,
                "class": "article",
                "width": 574.1176470588235
            },
            {
                "x": 1818.3726173396187,
                "height": 235.0,
                "type": "rect",
                "id": 15,
                "y": 668.0,
                "class": "article",
                "width": 553.1133428981349
            },
            {
                "x": 1811.3711826193892,
                "height": 4729.0,
                "type": "rect",
                "id": 16,
                "y": 967.0,
                "class": "article",
                "width": 573.1174420987908
            },
            {
                "x": 1854.3799959007993,
                "height": 530.0,
                "type": "rect",
                "id": 17,
                "y": 6254.0,
                "class": "article",
                "width": 1660.3402336544373
            },
            {
                "x": 1832.3754867800778,
                "height": 302.0,
                "type": "rect",
                "id": 18,
                "y": 6803.0,
                "class": "article",
                "width": 1682.3447427751587
            },
            {
                "x": 2396.4910842385734,
                "height": 226.0,
                "type": "rect",
                "id": 19,
                "y": 665.0,
                "class": "article",
                "width": 558.1143676982988
            },
            {
                "x": 2384.48862471818,
                "height": 4768.0,
                "type": "rect",
                "id": 20,
                "y": 928.0,
                "class": "article",
                "width": 590.1209264193482
            },
            {
                "x": 2976.609961057594,
                "height": 368.0,
                "type": "rect",
                "id": 21,
                "y": 669.0,
                "class": "article",
                "width": 1136.2328345972535
            },
            {
                "x": 2966.607911457266,
                "height": 1093.0,
                "type": "rect",
                "id": 22,
                "y": 1054.0,
                "class": "article",
                "width": 570.1168272186924
            },
            {
                "x": 2977.6101660176264,
                "height": 245.0,
                "type": "rect",
                "id": 23,
                "y": 2185.0,
                "class": "article",
                "width": 1065.2182824349252
            },
            {
                "x": 3125.64050010248,
                "height": 95.0,
                "type": "rect",
                "id": 24,
                "y": 2440.0,
                "class": "article",
                "width": 993.203525312564
            },
            {
                "x": 2973.6093461774954,
                "height": 1039.0,
                "type": "rect",
                "id": 25,
                "y": 2571.0,
                "class": "article",
                "width": 567.116212338594
            },
            {
                "x": 2978.6103709776594,
                "height": 118.0,
                "type": "rect",
                "id": 26,
                "y": 3640.0,
                "class": "article",
                "width": 1030.2111088337774
            },
            {
                "x": 2973.6093461774954,
                "height": 910.0,
                "type": "rect",
                "id": 27,
                "y": 3768.0,
                "class": "article",
                "width": 570.1168272186924
            },
            {
                "x": 2975.609756097561,
                "height": 112.0,
                "type": "rect",
                "id": 28,
                "y": 4717.0,
                "class": "article",
                "width": 1022.209469153515
            },
            {
                "x": 3112.6378356220534,
                "height": 97.0,
                "type": "rect",
                "id": 29,
                "y": 4844.0,
                "class": "article",
                "width": 1005.2059848329576
            },
            {
                "x": 2973.6093461774954,
                "height": 717.0,
                "type": "rect",
                "id": 30,
                "y": 4979.0,
                "class": "article",
                "width": 563.1153924984628
            },
            {
                "x": 3551.72781307645,
                "height": 103.0,
                "type": "rect",
                "id": 31,
                "y": 1051.0,
                "class": "article",
                "width": 562.11518753843
            },
            {
                "x": 3543.7261733961877,
                "height": 5942.0,
                "type": "rect",
                "id": 32,
                "y": 1162.0,
                "class": "article",
                "width": 577.1182619389219
            },
            {
                "x": 4232.8673908587825,
                "height": 164.0,
                "type": "rect",
                "id": 33,
                "y": 662.0,
                "class": "article",
                "width": 356.0729657716745
            },
            {
                "x": 4130.846484935438,
                "height": 6237.0,
                "type": "rect",
                "id": 34,
                "y": 861.0,
                "class": "article",
                "width": 574.1176470588235
            }
        ]
    }
]