[
    {
        "annotations": [
            {
                "id": 0,
                "x": 3602.242059,
                "type": "rect",
                "height": 236.0,
                "y": 647.0,
                "class": "title",
                "width": 924.5754619999998
            },
            {
                "id": 1,
                "x": 116.072244,
                "type": "rect",
                "height": 84.0,
                "y": 1143.25,
                "class": "title",
                "width": 534.332573
            },
            {
                "id": 2,
                "x": 754.469587,
                "type": "rect",
                "height": 104.0,
                "y": 2066.0,
                "class": "title",
                "width": 454.2827480000001
            },
            {
                "id": 3,
                "x": 730.45464,
                "type": "rect",
                "height": 96.0,
                "y": 2675.0,
                "class": "title",
                "width": 428.2665559999999
            },
            {
                "id": 4,
                "x": 762.474569,
                "type": "rect",
                "height": 96.0,
                "y": 5628.0,
                "class": "title",
                "width": 380.236662
            },
            {
                "id": 5,
                "x": 1250.778493,
                "type": "rect",
                "height": 81.5,
                "y": 1145.75,
                "class": "title",
                "width": 540.336309
            },
            {
                "id": 6,
                "x": 1901.183309,
                "type": "rect",
                "height": 94.0,
                "y": 5506.0,
                "class": "title",
                "width": 374.2329249999998
            },
            {
                "id": 7,
                "x": 2514.565082,
                "type": "rect",
                "height": 97.0,
                "y": 1157.8,
                "class": "title",
                "width": 1395.868798
            },
            {
                "id": 8,
                "x": 2636.641063,
                "type": "rect",
                "height": 98.77777777777783,
                "y": 1284.2222222222222,
                "class": "title",
                "width": 1373.8550969999997
            },
            {
                "id": 9,
                "x": 2475.540793,
                "type": "rect",
                "height": 108.0,
                "y": 3007.3333333333335,
                "class": "title",
                "width": 1020.6352499999998
            },
            {
                "id": 10,
                "x": 2386.485364,
                "type": "rect",
                "height": 91.75,
                "y": 4265.5,
                "class": "title",
                "width": 1002.6240400000002
            },
            {
                "id": 11,
                "x": 2440.518995,
                "type": "rect",
                "height": 94.79999999999927,
                "y": 4391.6,
                "class": "title",
                "width": 990.6165660000001
            },
            {
                "id": 12,
                "x": 2491.550758,
                "type": "rect",
                "height": 92.0,
                "y": 4518.0,
                "class": "title",
                "width": 1000.6227939999999
            },
            {
                "id": 13,
                "x": 3525.194104,
                "type": "rect",
                "height": 71.33333333333348,
                "y": 2944.6666666666665,
                "class": "title",
                "width": 541.3369319999997
            },
            {
                "id": 14,
                "x": 182.113349,
                "type": "rect",
                "height": 122.49999999999994,
                "y": 270.6666666666667,
                "class": "title",
                "width": 3772.3479339999994
            },
            {
                "id": 15,
                "x": 912.567988,
                "type": "rect",
                "height": 232.66666666666674,
                "y": 648.0,
                "class": "title",
                "width": 1492.9292090000001
            },
            {
                "id": 16,
                "x": 1817.130994,
                "type": "rect",
                "height": 87.33333333333394,
                "y": 2894.208333333333,
                "class": "title",
                "width": 1627.0126639999999
            },
            {
                "id": 17,
                "x": 2433.514636,
                "type": "rect",
                "height": 106.50000000000011,
                "y": 1002.4,
                "class": "title",
                "width": 2163.34648
            },
            {
                "id": 18,
                "x": 2389.487233,
                "type": "rect",
                "height": 96.5,
                "y": 2751.75,
                "class": "title",
                "width": 1621.0089270000003
            },
            {
                "id": 19,
                "x": 2387.485987,
                "type": "rect",
                "height": 92.5,
                "y": 5854.25,
                "class": "title",
                "width": 1003.624663
            },
            {
                "id": 20,
                "x": 2493.552003,
                "type": "rect",
                "height": 97.25,
                "y": 5980.333333333334,
                "class": "title",
                "width": 993.6184350000003
            },
            {
                "id": "1",
                "x": 100.062279,
                "type": "rect",
                "height": 5480.25,
                "y": 1378.0,
                "class": "article",
                "width": 554.3450290000001
            },
            {
                "id": "1",
                "x": 161.10027,
                "type": "rect",
                "height": 24.0,
                "y": 6876.0,
                "class": "article",
                "width": 111.06913
            },
            {
                "id": "2",
                "x": 693.431596,
                "type": "rect",
                "height": 405.8333333333335,
                "y": 2184.0,
                "class": "article",
                "width": 502.31264299999987
            },
            {
                "id": "3",
                "x": 666.414781,
                "type": "rect",
                "height": 2679.9999999999995,
                "y": 2864.3333333333335,
                "class": "article",
                "width": 566.352502
            },
            {
                "id": "4",
                "x": 679.422877,
                "type": "rect",
                "height": 1147.5,
                "y": 5804.166666666667,
                "class": "article",
                "width": 549.341915
            },
            {
                "id": "5",
                "x": 1241.772888,
                "type": "rect",
                "height": 5575.666666666666,
                "y": 1380.6666666666667,
                "class": "article",
                "width": 553.344405
            },
            {
                "id": "6",
                "x": 1819.13224,
                "type": "rect",
                "height": 1272.0,
                "y": 5684.333333333333,
                "class": "article",
                "width": 544.3388010000003
            },
            {
                "id": "7",
                "x": 2387.485987,
                "type": "rect",
                "height": 620.5,
                "y": 1673.5,
                "class": "article",
                "width": 184.11459400000012
            },
            {
                "id": "8",
                "x": 2388.48661,
                "type": "rect",
                "height": 1210.6666666666665,
                "y": 1459.0,
                "class": "article",
                "width": 542.3375550000001
            },
            {
                "id": "8",
                "x": 2951.837243,
                "type": "rect",
                "height": 1210.2142857142858,
                "y": 1460.2857142857142,
                "class": "article",
                "width": 540.3363090000003
            },
            {
                "id": "8",
                "x": 3515.187876,
                "type": "rect",
                "height": 1204.9166666666665,
                "y": 1456.75,
                "class": "article",
                "width": 553.3444060000002
            },
            {
                "id": "9",
                "x": 2381.48225,
                "type": "rect",
                "height": 991.1999999999998,
                "y": 3187.8,
                "class": "article",
                "width": 549.341915
            },
            {
                "id": "9",
                "x": 2949.835998,
                "type": "rect",
                "height": 993.6999999999998,
                "y": 3180.8,
                "class": "article",
                "width": 547.3406680000003
            },
            {
                "id": "12",
                "x": 2384.484119,
                "type": "rect",
                "height": 1077.6000000000004,
                "y": 4691.0,
                "class": "article",
                "width": 542.3375550000001
            },
            {
                "id": "12",
                "x": 2951.837243,
                "type": "rect",
                "height": 1073.583333333333,
                "y": 4693.25,
                "class": "article",
                "width": 539.3356859999999
            },
            {
                "id": "13",
                "x": 3512.186008,
                "type": "rect",
                "height": 3795.8333333333335,
                "y": 3124.6666666666665,
                "class": "article",
                "width": 557.3468969999999
            },
            {
                "id": "14",
                "x": 167.104007,
                "type": "rect",
                "height": 41.75,
                "y": 499.5,
                "class": "article",
                "width": 737.4589990000001
            },
            {
                "id": "14",
                "x": 1117.695661,
                "type": "rect",
                "height": 44.89999999999998,
                "y": 506.5,
                "class": "article",
                "width": 407.253477
            },
            {
                "id": "14",
                "x": 1801.12103,
                "type": "rect",
                "height": 43.80000000000001,
                "y": 504.2,
                "class": "article",
                "width": 1142.711231
            },
            {
                "id": "14",
                "x": 3555.212788,
                "type": "rect",
                "height": 21.80000000000001,
                "y": 502.2,
                "class": "article",
                "width": 1018.6340049999999
            },
            {
                "id": "15",
                "x": 720.448412,
                "type": "rect",
                "height": 53.33333333333326,
                "y": 1033.6666666666667,
                "class": "article",
                "width": 457.284617
            },
            {
                "id": "15",
                "x": 1838.144073,
                "type": "rect",
                "height": 1641.5,
                "y": 1036.0,
                "class": "article",
                "width": 497.3095290000001
            },
            {
                "id": "16",
                "x": 1813.128503,
                "type": "rect",
                "height": 2285.9999999999995,
                "y": 3134.3333333333335,
                "class": "article",
                "width": 548.3412909999997
            },
            {
                "id": "17",
                "x": 4083.541623,
                "type": "rect",
                "height": 5775.0,
                "y": 1191.0,
                "class": "article",
                "width": 579.3605980000002
            },
            {
                "id": "20",
                "x": 2383.483496,
                "type": "rect",
                "height": 803.7714285714283,
                "y": 6155.8,
                "class": "article",
                "width": 541.3369310000003
            },
            {
                "id": "20",
                "x": 2947.834752,
                "type": "rect",
                "height": 805.0,
                "y": 6154.0,
                "class": "article",
                "width": 541.3369319999997
            }
        ]
    }
]