[
    {
        "annotations": [
            {
                "class": "title", 
                "width": 64.03989199999998, 
                "y": 254.0, 
                "x": 230.143362, 
                "height": 44.0, 
                "type": "rect", 
                "id": "0"
            }, 
            {
                "class": "title", 
                "width": 1685.0496569999996, 
                "y": 252.85714285714286, 
                "x": 1465.913152, 
                "height": 45.714285714285694, 
                "type": "rect", 
                "id": "1"
            }, 
            {
                "class": "title", 
                "width": 535.333471, 
                "y": 524.0, 
                "x": 159.099107, 
                "height": 63.200000000000045, 
                "type": "rect", 
                "id": "4"
            }, 
            {
                "class": "title", 
                "width": 533.332225, 
                "y": 707.3333333333334, 
                "x": 160.09973, 
                "height": 42.0, 
                "type": "rect", 
                "id": "4"
            }, 
            {
                "class": "title", 
                "width": 313.19509700000003, 
                "y": 765.0, 
                "x": 266.165801, 
                "height": 45.5, 
                "type": "rect", 
                "id": "4"
            }, 
            {
                "class": "title", 
                "width": 392.2443380000001, 
                "y": 5938.0, 
                "x": 208.129649, 
                "height": 43.75, 
                "type": "rect", 
                "id": "8"
            }, 
            {
                "class": "title", 
                "width": 400.24932399999994, 
                "y": 6143.75, 
                "x": 188.117183, 
                "height": 43.75, 
                "type": "rect", 
                "id": "8"
            }, 
            {
                "class": "title", 
                "width": 256.1595680000001, 
                "y": 6433.0, 
                "x": 313.195097, 
                "height": 43.5, 
                "type": "rect", 
                "id": "8"
            }, 
            {
                "class": "title", 
                "width": 522.325369, 
                "y": 6577.333333333333, 
                "x": 170.105963, 
                "height": 76.0, 
                "type": "rect", 
                "id": "8"
            }, 
            {
                "class": "title", 
                "width": 2184.360689, 
                "y": 5022.666666666667, 
                "x": 1387.864534, 
                "height": 71.83333333333303, 
                "type": "rect", 
                "id": "10"
            }, 
            {
                "class": "title", 
                "width": 2533.578226, 
                "y": 5333.4, 
                "x": 1925.199252, 
                "height": 58.600000000000364, 
                "type": "rect", 
                "id": "10"
            }, 
            {
                "class": "title", 
                "width": 2139.3326399999996, 
                "y": 5496.666666666667, 
                "x": 1700.059007, 
                "height": 42.55555555555566, 
                "type": "rect", 
                "id": "11"
            }, 
            {
                "class": "title", 
                "width": 538.335343, 
                "y": 554.6666666666666, 
                "x": 1830.140037, 
                "height": 62.0, 
                "type": "rect", 
                "id": "14"
            }, 
            {
                "class": "title", 
                "width": 533.3322250000001, 
                "y": 703.0, 
                "x": 1834.142531, 
                "height": 43.25, 
                "type": "rect", 
                "id": "14"
            }, 
            {
                "class": "title", 
                "width": 394.245584, 
                "y": 762.3333333333334, 
                "x": 1901.184293, 
                "height": 41.0, 
                "type": "rect", 
                "id": "14"
            }, 
            {
                "class": "title", 
                "width": 2471.5395799999997, 
                "y": 3578.6666666666665, 
                "x": 2055.280283, 
                "height": 103.55555555555566, 
                "type": "rect", 
                "id": "10"
            }, 
            {
                "class": "title", 
                "width": 104.06482400000004, 
                "y": 6447.0, 
                "x": 1819.133181, 
                "height": 51.0, 
                "type": "rect", 
                "id": "16"
            }, 
            {
                "class": "title", 
                "width": 1128.703095, 
                "y": 6661.666666666667, 
                "x": 1614.005402, 
                "height": 46.83333333333303, 
                "type": "rect", 
                "id": "17"
            }, 
            {
                "class": "title", 
                "width": 996.6208189999998, 
                "y": 734.1666666666666, 
                "x": 2478.543943, 
                "height": 39.83333333333337, 
                "type": "rect", 
                "id": "40"
            }, 
            {
                "class": "title", 
                "width": 430.26802399999997, 
                "y": 2953.0, 
                "x": 2394.491585, 
                "height": 58.0, 
                "type": "rect", 
                "id": "21"
            }, 
            {
                "class": "title", 
                "width": 438.2730099999999, 
                "y": 3037.3333333333335, 
                "x": 2446.523998, 
                "height": 62.33333333333303, 
                "type": "rect", 
                "id": "21"
            }, 
            {
                "class": "title", 
                "width": 461.28734799999984, 
                "y": 3121.0, 
                "x": 2468.53771, 
                "height": 58.0, 
                "type": "rect", 
                "id": "21"
            }, 
            {
                "class": "title", 
                "width": 40.02493199999981, 
                "y": 6694.0, 
                "x": 3446.146686, 
                "height": 68.0, 
                "type": "rect", 
                "id": "25"
            }, 
            {
                "class": "title", 
                "width": 444.27675100000033, 
                "y": 1934.3333333333333, 
                "x": 3045.897361, 
                "height": 81.33333333333348, 
                "type": "rect", 
                "id": "23"
            }, 
            {
                "class": "title", 
                "width": 620.3864540000004, 
                "y": 6769.0, 
                "x": 2865.785165, 
                "height": 102.0, 
                "type": "rect", 
                "id": "24"
            }, 
            {
                "class": "title", 
                "width": 68.0423850000002, 
                "y": 6888.0, 
                "x": 3428.135466, 
                "height": 72.0, 
                "type": "rect", 
                "id": "25"
            }, 
            {
                "class": "title", 
                "width": 1015.6326610000001, 
                "y": 2341.5, 
                "x": 3570.223977, 
                "height": 87.5, 
                "type": "rect", 
                "id": "31"
            }, 
            {
                "class": "title", 
                "width": 1018.6345320000005, 
                "y": 2451.8571428571427, 
                "x": 3569.223353, 
                "height": 47.571428571428896, 
                "type": "rect", 
                "id": "31"
            }, 
            {
                "class": "title", 
                "width": 1015.6326620000004, 
                "y": 2515.6666666666665, 
                "x": 3570.223977, 
                "height": 42.77777777777783, 
                "type": "rect", 
                "id": "31"
            }, 
            {
                "class": "title", 
                "width": 1016.633284, 
                "y": 2570.0, 
                "x": 3570.223977, 
                "height": 50.42857142857156, 
                "type": "rect", 
                "id": "31"
            }, 
            {
                "class": "title", 
                "width": 701.4369409999995, 
                "y": 2633.5714285714284, 
                "x": 3727.321837, 
                "height": 42.42857142857156, 
                "type": "rect", 
                "id": "31"
            }, 
            {
                "class": "title", 
                "width": 750.4674839999998, 
                "y": 2717.0, 
                "x": 3706.308747, 
                "height": 100.0, 
                "type": "rect", 
                "id": "31"
            }, 
            {
                "class": "title", 
                "width": 1014.6320379999993, 
                "y": 2906.8, 
                "x": 3571.2246, 
                "height": 56.19999999999982, 
                "type": "rect", 
                "id": "37"
            }, 
            {
                "class": "title", 
                "width": 1014.6320380000002, 
                "y": 3011.125, 
                "x": 3569.223353, 
                "height": 44.875, 
                "type": "rect", 
                "id": "37"
            }, 
            {
                "class": "title", 
                "width": 1014.6320379999993, 
                "y": 3068.0, 
                "x": 3570.223977, 
                "height": 45.625, 
                "type": "rect", 
                "id": "37"
            }, 
            {
                "class": "title", 
                "width": 1010.6295449999993, 
                "y": 3132.125, 
                "x": 3570.223977, 
                "height": 39.75, 
                "type": "rect", 
                "id": "37"
            }, 
            {
                "class": "title", 
                "width": 394.24558499999966, 
                "y": 3185.3333333333335, 
                "x": 3876.41471, 
                "height": 44.33333333333303, 
                "type": "rect", 
                "id": "37"
            }, 
            {
                "class": "title", 
                "width": 1012.6307919999995, 
                "y": 3278.5, 
                "x": 3572.225223, 
                "height": 72.0, 
                "type": "rect", 
                "id": "37"
            }, 
            {
                "class": "title", 
                "width": 991.617702, 
                "y": 6303.291666666666, 
                "x": 189.117806, 
                "height": 46.70833333333394, 
                "type": "rect", 
                "id": "38"
            }, 
            {
                "class": "title", 
                "width": 1535.9567849999999, 
                "y": 6526.0, 
                "x": 1612.004155, 
                "height": 99.25, 
                "type": "rect", 
                "id": "17"
            }, 
            {
                "class": "title", 
                "width": 1006.6270519999998, 
                "y": 1572.0, 
                "x": 2429.513401, 
                "height": 59.0, 
                "type": "rect", 
                "id": "40"
            }, 
            {
                "class": "title", 
                "width": 2117.3189279999997, 
                "y": 378.75, 
                "x": 1863.160607, 
                "height": 87.58333333333331, 
                "type": "rect", 
                "id": "41"
            }, 
            {
                "class": "article", 
                "width": 538.3353420000001, 
                "y": 655.5714285714286, 
                "x": 1267.789736, 
                "height": 2799.4285714285716, 
                "type": "rect", 
                "id": "1"
            }, 
            {
                "class": "article", 
                "width": 558.347808, 
                "y": 888.4, 
                "x": 134.083524, 
                "height": 4070.266666666667, 
                "type": "rect", 
                "id": "4"
            }, 
            {
                "class": "article", 
                "width": 489.304799, 
                "y": 6698.5, 
                "x": 191.119053, 
                "height": 239.21428571428532, 
                "type": "rect", 
                "id": "8"
            }, 
            {
                "class": "article", 
                "width": 789.4917929999997, 
                "y": 6177.0, 
                "x": 3738.328693, 
                "height": 366.0, 
                "type": "rect", 
                "id": "10"
            }, 
            {
                "class": "article", 
                "width": 2814.753377, 
                "y": 5418.222222222223, 
                "x": 1720.071473, 
                "height": 67.15277777777737, 
                "type": "rect", 
                "id": "10"
            }, 
            {
                "class": "article", 
                "width": 3113.9397460000005, 
                "y": 5547.625, 
                "x": 1407.877, 
                "height": 879.5972222222226, 
                "type": "rect", 
                "id": "11"
            }, 
            {
                "class": "article", 
                "width": 1178.7342620000004, 
                "y": 5922.444444444444, 
                "x": 3319.067525, 
                "height": 180.15555555555602, 
                "type": "rect", 
                "id": "11"
            }, 
            {
                "class": "article", 
                "width": 408.25431100000014, 
                "y": 6125.0, 
                "x": 3668.285061, 
                "height": 425.0, 
                "type": "rect", 
                "id": "11"
            }, 
            {
                "class": "article", 
                "width": 540.336589, 
                "y": 886.0, 
                "x": 1827.138167, 
                "height": 2572.0, 
                "type": "rect", 
                "id": "14"
            }, 
            {
                "class": "article", 
                "width": 1129.7037189999999, 
                "y": 6743.0, 
                "x": 1617.007272, 
                "height": 189.78571428571468, 
                "type": "rect", 
                "id": "17"
            }, 
            {
                "class": "article", 
                "width": 539.3359649999998, 
                "y": 3264.125, 
                "x": 2391.489715, 
                "height": 194.375, 
                "type": "rect", 
                "id": "21"
            }, 
            {
                "class": "article", 
                "width": 542.3378359999997, 
                "y": 2046.9, 
                "x": 2952.839393, 
                "height": 1412.1, 
                "type": "rect", 
                "id": "23"
            }, 
            {
                "class": "article", 
                "width": 78.04861900000014, 
                "y": 2348.0, 
                "x": 3347.084978, 
                "height": 49.0, 
                "type": "rect", 
                "id": "23"
            }, 
            {
                "class": "article", 
                "width": 293.18263100000013, 
                "y": 2838.5, 
                "x": 3931.448992, 
                "height": 32.5, 
                "type": "rect", 
                "id": "31"
            }, 
            {
                "class": "article", 
                "width": 317.19759, 
                "y": 6388.666666666667, 
                "x": 273.170164, 
                "height": 35.66666666666606, 
                "type": "rect", 
                "id": "38"
            }, 
            {
                "class": "article", 
                "width": 464.289217, 
                "y": 6419.6, 
                "x": 762.474964, 
                "height": 483.89999999999964, 
                "type": "rect", 
                "id": "38"
            }, 
            {
                "class": "article", 
                "width": 1081.6738, 
                "y": 1682.1666666666667, 
                "x": 2390.489092, 
                "height": 1217.0833333333333, 
                "type": "rect", 
                "id": "40"
            }, 
            {
                "class": "article", 
                "width": 1110.6918759999999, 
                "y": 555.3333333333334, 
                "x": 3518.191565, 
                "height": 1637.1666666666665, 
                "type": "rect", 
                "id": "41"
            }
        ]
    }
]